mcmd/__init__.py
mcmd/__main__.py
mcmd/args/__init__.py
mcmd/args/_factory.py
mcmd/args/_formatter.py
mcmd/args/_raising_parser.py
mcmd/args/actions.py
mcmd/args/errors.py
mcmd/args/parser.py
mcmd/commands/__init__.py
mcmd/commands/_registry.py
mcmd/commands/add.py
mcmd/commands/config.py
mcmd/commands/delete.py
mcmd/commands/disable.py
mcmd/commands/enable.py
mcmd/commands/give.py
mcmd/commands/history.py
mcmd/commands/import_.py
mcmd/commands/make.py
mcmd/commands/ping.py
mcmd/commands/run.py
mcmd/commands/script.py
mcmd/commands/set.py
mcmd/config/__init__.py
mcmd/config/config.py
mcmd/config/defaults.yaml
mcmd/config/loader.py
mcmd/core/__init__.py
mcmd/core/command.py
mcmd/core/compatibility.py
mcmd/core/errors.py
mcmd/core/history.py
mcmd/core/store.py
mcmd/core/update_checker.py
mcmd/core/context/__init__.py
mcmd/core/context/_context_holder.py
mcmd/core/context/base_context.py
mcmd/core/context/home_context.py
mcmd/github/__init__.py
mcmd/github/client.py
mcmd/io/__init__.py
mcmd/io/ask.py
mcmd/io/io.py
mcmd/io/kbhit.py
mcmd/io/logging.py
mcmd/molgenis/__init__.py
mcmd/molgenis/api.py
mcmd/molgenis/auth.py
mcmd/molgenis/client.py
mcmd/molgenis/principals.py
mcmd/molgenis/request_handler.py
mcmd/molgenis/resources.py
mcmd/molgenis/rest_api_v2_mapper.py
mcmd/molgenis/system.py
mcmd/molgenis/version.py
mcmd/molgenis/security/__init__.py
mcmd/molgenis/security/permission.py
mcmd/molgenis/security/permission_manager.py
mcmd/molgenis/security/permissions_api.py
mcmd/molgenis/security/security.py
mcmd/script/__init__.py
mcmd/script/options.py
mcmd/script/script_runner.py
mcmd/script/model/__init__.py
mcmd/script/model/lines.py
mcmd/script/model/script.py
mcmd/script/model/statements.py
mcmd/script/model/templates.py
mcmd/script/model/types_.py
mcmd/script/parser/__init__.py
mcmd/script/parser/_parse_state.py
mcmd/script/parser/dependency_resolver.py
mcmd/script/parser/errors.py
mcmd/script/parser/line_combiner.py
mcmd/script/parser/line_parser.py
molgenis_commander-1.11.1.dist-info/LICENSE
molgenis_commander-1.11.1.dist-info/METADATA
molgenis_commander-1.11.1.dist-info/WHEEL
molgenis_commander-1.11.1.dist-info/entry_points.txt
molgenis_commander-1.11.1.dist-info/top_level.txt
molgenis_commander-1.11.1.dist-info/RECORD
