Metadata-Version: 2.1
Name: molgenis-commander
Version: 1.11.1
Summary: A command line interface for Molgenis
Home-page: https://github.com/molgenis/molgenis-tools-commander
Author: Tommy de Boer
Author-email: tommydeboer4@gmail.com
License: GNU Lesser General Public License 3.0
Platform: UNKNOWN
Requires-Dist: attrs (==21.2.0)
Requires-Dist: colorama (==0.4.4)
Requires-Dist: halo (==0.0.31)
Requires-Dist: Jinja2 (==3.0.3)
Requires-Dist: packaging (==20.9)
Requires-Dist: parsy (==1.3.0)
Requires-Dist: polling (==0.3.2)
Requires-Dist: PyGithub (==1.55)
Requires-Dist: questionary (==1.10.0)
Requires-Dist: rainbow-logging-handler (==2.2.2)
Requires-Dist: requests (==2.27.1)
Requires-Dist: ruamel.yaml (==0.17.16)
